README.rst
setup.cfg
setup.py
GenBankQC.egg-info/PKG-INFO
GenBankQC.egg-info/SOURCES.txt
GenBankQC.egg-info/dependency_links.txt
GenBankQC.egg-info/entry_points.txt
GenBankQC.egg-info/requires.txt
GenBankQC.egg-info/top_level.txt
genbankqc/Genbank.py
genbankqc/Genome.py
genbankqc/Species.py
genbankqc/__init__.py
genbankqc/__main__.py
genbankqc/mash.py
test/__init__.py
test/conftest.py
test/test_Genbank.py
test/test_Genome.py
test/test_Species.py
test/test___main__.py