Metadata-Version: 1.2
Name: GenBankQC
Version: 0.2a0
Summary: "Automated quality control for GenBank genomes."
Home-page: https://github.com/andrewsanchez/genbankqc
Author: Andrew Sanchez
Author-email: inbox.asanchez@gmail.com
License: BSD-3-Clause
Keywords: NCBI bioinformatics genomics
Platform: UNKNOWN
Classifier: Topic :: Scientific/Engineering :: Bio-Informatics
Classifier: Programming Language :: Python :: 3.6
Classifier: Operating System :: POSIX :: Linux
Classifier: License :: OSI Approved :: MIT License
Classifier: Intended Audience :: Science/Research
Classifier: Environment :: Console
Classifier: Development Status :: 3 - Alpha
Requires-Python: >=3.4
